ChronicleLogger/ChronicleLogger.py
ChronicleLogger/Suroot.py
ChronicleLogger/TimeProvider.py
ChronicleLogger/__init__.py
chroniclelogger-1.2.3.dist-info/METADATA
chroniclelogger-1.2.3.dist-info/WHEEL
chroniclelogger-1.2.3.dist-info/top_level.txt
chroniclelogger-1.2.3.dist-info/zip-safe
chroniclelogger-1.2.3.dist-info/RECORD
