Metadata-Version: 2.4
Name: ChronicleLogger
Version: 1.2.3
Summary: Privilege-aware, auto-rotating daily logger for Linux daemons & CLI tools
Home-page: https://github.com/Wilgat/ChronicleLogger
Author: Wilgat Wong
Author-email: wilgat.wong@gmail.com
License: MIT
Project-URL: Bug Tracker, https://github.com/Wilgat/ChronicleLogger/issues
Project-URL: Source, https://github.com/Wilgat/ChronicleLogger
Keywords: logging linux daemon sudo privilege log rotation daily
Classifier: Programming Language :: Python :: 2
Classifier: Programming Language :: Python :: 2.7
Classifier: Programming Language :: Python :: 3
Classifier: Programming Language :: Python :: 3.8
Classifier: Programming Language :: Python :: 3.9
Classifier: Programming Language :: Python :: 3.10
Classifier: Programming Language :: Python :: 3.11
Classifier: Programming Language :: Python :: 3.12
Classifier: Programming Language :: Python :: 3.13
Classifier: License :: OSI Approved :: MIT License
Classifier: Operating System :: POSIX :: Linux
Classifier: Topic :: System :: Logging
Classifier: Development Status :: 5 - Production/Stable
Classifier: Intended Audience :: Developers
Requires-Python: >=2.7, !=3.0.*, !=3.1.*, !=3.2.*, !=3.3.*, !=3.4.*
Dynamic: author
Dynamic: author-email
Dynamic: classifier
Dynamic: description
Dynamic: description-content-type
Dynamic: home-page
Dynamic: keywords
Dynamic: license
Dynamic: project-url
Dynamic: requires-python
Dynamic: summary
